yanytapi/__init__.py
yanytapi/search.py
yanytapi/tests/__init__.py
yanytapi/tests/test_search.py
yanytapi-2.0.0.dist-info/LICENSE
yanytapi-2.0.0.dist-info/METADATA
yanytapi-2.0.0.dist-info/WHEEL
yanytapi-2.0.0.dist-info/top_level.txt
yanytapi-2.0.0.dist-info/RECORD
