Metadata-Version: 2.1
Name: yanytapi
Version: 2.0.0
Summary: Python wrapper for the New York Times Article Search API
Home-page: https://github.com/neverna-ptitsa/yanytapi
Author: Ed Kohlwey
Author-email: neverna-ptitsa@gmail.com
License: MIT
Platform: UNKNOWN
Classifier: License :: OSI Approved :: MIT License
Classifier: Programming Language :: Python
Classifier: Programming Language :: Python :: 3
Classifier: Programming Language :: Python :: 3.6
Classifier: Programming Language :: Python :: Implementation :: CPython
Classifier: Programming Language :: Python :: Implementation :: PyPy
Requires-Python: >=3.6.0
Requires-Dist: requests (>=2.7.0)
